cglbtrial2/__init__ .py
cglbtrial2/conversion.py
cglbtrial2-0.2.0.dist-info/METADATA
cglbtrial2-0.2.0.dist-info/WHEEL
cglbtrial2-0.2.0.dist-info/RECORD
